Metadata-Version: 2.1
Name: suite2p-haisslab
Version: 0.15.1
Summary: Pipeline for calcium imaging
Author: Marius Pachitariu, Carsen Stringer
Author-Email: Timothe Jost-Mousseau <timothe.jost-mousseau@pasteur.fr>
License: GPLv3
Classifier: License :: OSI Approved :: GNU General Public License v3 (GPLv3)
Classifier: Operating System :: OS Independent
Classifier: Programming Language :: Python :: 3
Project-URL: Homepage, https://github.com/JostTim/suite2p
Requires-Python: >=3.11
Requires-Dist: cellpose
Requires-Dist: matplotlib
Requires-Dist: natsort
Requires-Dist: numba>=0.57.0
Requires-Dist: numpy>=1.24.3
Requires-Dist: rastermap>=0.9.0
Requires-Dist: scanimage-tiff-reader>=1.4.1
Requires-Dist: scikit-learn
Requires-Dist: scipy>=1.9.0
Requires-Dist: tifffile
Requires-Dist: mkl-fft
Provides-Extra: gui
Requires-Dist: PyQt5; extra == "gui"
Requires-Dist: pyqt6; extra == "gui"
Requires-Dist: pyqt6.sip; extra == "gui"
Requires-Dist: pyqtgraph; extra == "gui"
Requires-Dist: qtpy; extra == "gui"
Requires-Dist: pyqt5-qt5==5.15.2; extra == "gui"
Provides-Extra: nwb
Requires-Dist: pynwb>=2.3.2; extra == "nwb"
Provides-Extra: io
Requires-Dist: h5py; extra == "io"
Requires-Dist: nd2; extra == "io"
Requires-Dist: opencv-python-headless; extra == "io"
Requires-Dist: paramiko; extra == "io"
Requires-Dist: sbxreader; extra == "io"
Requires-Dist: xmltodict; extra == "io"
Provides-Extra: tests
Requires-Dist: pynwb>=2.3.2; extra == "tests"
Requires-Dist: pytest; extra == "tests"
Requires-Dist: pytest-qt>3.3.0; extra == "tests"
Requires-Dist: tenacity; extra == "tests"
Requires-Dist: tqdm; extra == "tests"
Provides-Extra: all
Requires-Dist: PyQt5; extra == "all"
Requires-Dist: h5py; extra == "all"
Requires-Dist: nd2; extra == "all"
Requires-Dist: opencv-python-headless; extra == "all"
Requires-Dist: paramiko; extra == "all"
Requires-Dist: pynwb>=2.3.2; extra == "all"
Requires-Dist: pynwb>=2.3.2; extra == "all"
Requires-Dist: pyqt6; extra == "all"
Requires-Dist: pyqt6.sip; extra == "all"
Requires-Dist: pyqtgraph; extra == "all"
Requires-Dist: pytest; extra == "all"
Requires-Dist: pytest-qt>3.3.0; extra == "all"
Requires-Dist: qtpy; extra == "all"
Requires-Dist: sbxreader; extra == "all"
Requires-Dist: tenacity; extra == "all"
Requires-Dist: tqdm; extra == "all"
Requires-Dist: xmltodict; extra == "all"
Requires-Dist: dcimg; extra == "all"
